deepwell_processing_shared/__init__.py
deepwell_processing_shared/common/__init__.py
deepwell_processing_shared/common/resources.py
deepwell_processing_shared/common/util.py
deepwell_processing_shared/schema/__init__.py
deepwell_processing_shared-0.1.5.dist-info/METADATA
deepwell_processing_shared-0.1.5.dist-info/WHEEL
deepwell_processing_shared-0.1.5.dist-info/RECORD
